orcakit_runtime_inmem/__init__.py
orcakit_runtime_inmem/checkpoint.py
orcakit_runtime_inmem/database.py
orcakit_runtime_inmem/inmem_stream.py
orcakit_runtime_inmem/lifespan.py
orcakit_runtime_inmem/metrics.py
orcakit_runtime_inmem/ops.py
orcakit_runtime_inmem/queue.py
orcakit_runtime_inmem/retry.py
orcakit_runtime_inmem/store.py
orcakit_runner_inmem-0.18.0.dist-info/METADATA
orcakit_runner_inmem-0.18.0.dist-info/WHEEL
orcakit_runner_inmem-0.18.0.dist-info/RECORD
